pyfdempp/__init__.py
pyfdempp/aggregate_storage.py
pyfdempp/complete_BD_thread_pool_generators.py
pyfdempp/complete_PLT_thread_pool_generators.py
pyfdempp/complete_UCS_thread_pool_generators.py
pyfdempp/direct_shear_thread_pool_generators.py
pyfdempp/extract_cell_thread_pool_generators.py
pyfdempp/extract_thread_pool_generators.py
pyfdempp/extract_threshold_thread_pool_generators.py
pyfdempp/formatting_codes.py
pyfdempp/model_reader.py
pyfdempp/pyfdempp.py
pyfdempp-0.2.dist-info/METADATA
pyfdempp-0.2.dist-info/WHEEL
pyfdempp-0.2.dist-info/top_level.txt
pyfdempp-0.2.dist-info/RECORD
