Metadata-Version: 2.1
Name: pyfdempp
Version: 0.2
Summary: Performs transformations on hybrid finite-discrete element method (FDEM) models with an unstructured grid in vtk/vtu/vtp format.
Home-page: https://openfdem.com/
Author: Grasselli's Geomechanics Group - University of Toronto
Author-email: 
License: UNKNOWN
Keywords: example documentation tutorial
Platform: UNKNOWN
Requires-Python: >=3.5
Requires-Dist: joblib
Requires-Dist: numpy (>=1.0)
Requires-Dist: pandas (>=0.0)
Requires-Dist: pyvista (>=0.35)
Requires-Dist: tqdm
